default_metrics_asgi/__init__.py
default_metrics_asgi/prometheus.py
default_metrics_asgi-0.1.0.dist-info/LICENSE
default_metrics_asgi-0.1.0.dist-info/METADATA
default_metrics_asgi-0.1.0.dist-info/WHEEL
default_metrics_asgi-0.1.0.dist-info/RECORD
