Metadata-Version: 2.3
Name: default_metrics_asgi
Version: 0.1.0
Summary: A helper package for collecting default Prometheus metrics in ASGI applications.
License: MIT
Author: kimberly
Author-email: 45748394+kquiet@users.noreply.github.com
Requires-Python: >=3.9
Classifier: License :: OSI Approved :: MIT License
Classifier: Programming Language :: Python :: 3
Classifier: Programming Language :: Python :: 3.9
Classifier: Programming Language :: Python :: 3.10
Classifier: Programming Language :: Python :: 3.11
Classifier: Programming Language :: Python :: 3.12
Classifier: Programming Language :: Python :: 3.13
Requires-Dist: prometheus-client (>=0.22.1,<1.0.0)
Requires-Dist: starlette (>=0.47.2,<1.0.0)
Project-URL: Repository, https://github.com/kquiet/python_default_metrics_asgi
